pymoodleapi/api/api.py
pymoodleapi/api/api_response_objects.py
pymoodleapi/api/client.py
pymoodleapi/api/endpoints.py
pymoodleapi/settings.py
pymoodleapi-3.1.0.dist-info/LICENSE
pymoodleapi-3.1.0.dist-info/METADATA
pymoodleapi-3.1.0.dist-info/WHEEL
pymoodleapi-3.1.0.dist-info/RECORD
