Metadata-Version: 2.1
Name: pymoodleapi
Version: 3.1.0
Summary: Python wrapper for Moodle REST API
Home-page: https://github.com/vlaszdunov/moodle-api
License: MIT
Author: vlaszdunov
Author-email: design@formo.design
Requires-Python: >=3.8,<4.0
Classifier: License :: OSI Approved :: MIT License
Classifier: Programming Language :: Python :: 3
Classifier: Programming Language :: Python :: 3.8
Classifier: Programming Language :: Python :: 3.9
Classifier: Programming Language :: Python :: 3.10
Classifier: Programming Language :: Python :: 3.11
Classifier: Programming Language :: Python :: 3.12
Requires-Dist: python-dotenv (>=1.0.1,<2.0.0)
Requires-Dist: requests (>=2.32.3,<3.0.0)
Project-URL: Repository, https://github.com/vlaszdunov/moodle-api
